beetsplug/quicktag/__init__.py
beetsplug/quicktag/app.py
beetsplug/quicktag/widgets/custom_selection_list.py
beetsplug/quicktag/widgets/input_with_label.py
beetsplug/quicktag/widgets/playback.py
beetsplug/quicktag/widgets/playback_progress.py
beets_quicktag-0.1.0.dist-info/METADATA
beets_quicktag-0.1.0.dist-info/WHEEL
beets_quicktag-0.1.0.dist-info/top_level.txt
beets_quicktag-0.1.0.dist-info/RECORD
