Metadata-Version: 2.4
Name: beets-quicktag
Version: 0.1.0
Summary: A beets plugin for quickly tagging tracks with customizable attributes
Requires-Python: >=3.11
Requires-Dist: beets>=2.3.0
Requires-Dist: just-playback>=0.1.8
Requires-Dist: textual>=3.2.0
